CODE_OF_CONDUCT.md
LICENSE
MANIFEST.in
README.md
requirements.txt
setup.cfg
setup.py
access_face_vision/__init__.py
access_face_vision/__main__.py
access_face_vision/about.py
access_face_vision/access_logger.py
access_face_vision/component.py
access_face_vision/embedding_generator.py
access_face_vision/exceptions.py
access_face_vision/face_detector.py
access_face_vision/face_encoder.py
access_face_vision/face_group_manager.py
access_face_vision/face_recogniser.py
access_face_vision/server.py
access_face_vision/train.py
access_face_vision/train_face_recognition_model.py
access_face_vision/utils.py
access_face_vision.egg-info/PKG-INFO
access_face_vision.egg-info/SOURCES.txt
access_face_vision.egg-info/dependency_links.txt
access_face_vision.egg-info/requires.txt
access_face_vision.egg-info/top_level.txt
access_face_vision/sink/__init__.py
access_face_vision/sink/display.py
access_face_vision/sink/video_writer.py
access_face_vision/source/__init__.py
access_face_vision/source/camera.py
access_face_vision/source/image_reader.py