Metadata-Version: 2.1
Name: access-face-vision
Version: 0.0.3
Summary: UNKNOWN
Home-page: https://github.com/accessai/access-face-vision
Author: ConvexHull Technology Private Limited
Author-email: support@accessai.co
Maintainer: Majeed Khan
Maintainer-email: majeed.khan@accessai.co
License: Apache 2.0
Platform: UNKNOWN
Classifier: Intended Audience :: Developers
Classifier: License :: OSI Approved :: Apache Software License
Classifier: Programming Language :: Python
Classifier: Programming Language :: Python :: 3.6
Classifier: Operating System :: OS Independent
Classifier: Topic :: Software Development :: Libraries
